helicone_helpers/__init__.py
helicone_helpers/manual_logger.py
helicone_helpers/prompt_manager.py
helicone_helpers/template_manager.py
helicone_helpers/types.py
helicone_helpers-1.2.1.dist-info/METADATA
helicone_helpers-1.2.1.dist-info/WHEEL
helicone_helpers-1.2.1.dist-info/RECORD
