Metadata-Version: 2.3
Name: helicone_helpers
Version: 1.2.1
Summary: A Python wrapper for some of Helicone's common functionalities
License: Apache-2.0
Author: Helicone, Inc.
Author-email: help@helicone.ai
Requires-Python: >=3.8,<4.0
Classifier: License :: OSI Approved :: Apache Software License
Classifier: Programming Language :: Python :: 3
Classifier: Programming Language :: Python :: 3.8
Classifier: Programming Language :: Python :: 3.9
Classifier: Programming Language :: Python :: 3.10
Classifier: Programming Language :: Python :: 3.11
Classifier: Programming Language :: Python :: 3.12
Classifier: Programming Language :: Python :: 3.13
Requires-Dist: h11 (>=0.16.0)
Requires-Dist: httpx (>=0.28.0,<0.29.0)
Requires-Dist: requests (>=2.32.3,<3.0.0)
Project-URL: Homepage, https://www.helicone.ai
Project-URL: Repository, https://github.com/Helicone/helicone/tree/main/sdk/python/helpers
